antispam/__init__.py
antispam/anti_spam_handler.py
antispam/base_plugin.py
antispam/core.py
antispam/deprecation.py
antispam/exceptions.py
antispam/factory.py
antispam/plugin_cache.py
antispam/util.py
antispam/abc/__init__.py
antispam/abc/cache.py
antispam/abc/lib.py
antispam/caches/__init__.py
antispam/caches/memory/__init__.py
antispam/caches/memory/memory.py
antispam/caches/mongo/__init__.py
antispam/caches/mongo/document.py
antispam/caches/mongo/mongo_cache.py
antispam/caches/redis/__init__.py
antispam/caches/redis/redis.py
antispam/dataclasses/__init__.py
antispam/dataclasses/core.py
antispam/dataclasses/guild.py
antispam/dataclasses/member.py
antispam/dataclasses/message.py
antispam/dataclasses/options.py
antispam/dataclasses/propagate_data.py
antispam/enums/__init__.py
antispam/enums/ignored_types.py
antispam/enums/library.py
antispam/enums/reset_type.py
antispam/libs/__init__.py
antispam/libs/dpy.py
antispam/libs/lib_hikari.py
antispam/libs/dpy_forks/__init__.py
antispam/libs/dpy_forks/base_fork.py
antispam/libs/dpy_forks/lib_disnake.py
antispam/libs/dpy_forks/lib_enhanced_dpy.py
antispam/libs/dpy_forks/lib_nextcord.py
antispam/libs/shared/__init__.py
antispam/libs/shared/base.py
antispam/libs/shared/substitute_args.py
antispam/libs/shared/timed_cache.py
antispam/plugins/__init__.py
antispam/plugins/admin_logs.py
antispam/plugins/anti_mass_mention.py
antispam/plugins/anti_spam_tracker.py
antispam/plugins/max_message_limiter.py
antispam/plugins/stats.py
Discord_Anti_Spam-1.9.1.dist-info/LICENSE
Discord_Anti_Spam-1.9.1.dist-info/METADATA
Discord_Anti_Spam-1.9.1.dist-info/WHEEL
Discord_Anti_Spam-1.9.1.dist-info/top_level.txt
Discord_Anti_Spam-1.9.1.dist-info/RECORD
