Metadata-Version: 2.1
Name: Discord-Anti-Spam
Version: 1.9.1
Summary: An easy to use package for anti-spam features in python discord libraries.
Home-page: UNKNOWN
Author: Skelmis
Author-email: ethan@koldfusion.xyz
License: UNKNOWN
Project-URL: Support server, https://discord.gg/BqPNSH2jPg
Project-URL: Issue tracker, https://github.com/Skelmis/DPY-Anti-Spam/issues
Project-URL: Documentation, https://dpy-anti-spam.readthedocs.io/en/latest
Project-URL: Homepage, https://github.com/Skelmis/DPY-Anti-Spam
Platform: UNKNOWN
Classifier: Programming Language :: Python :: 3
Classifier: License :: OSI Approved :: MIT License
Classifier: Operating System :: OS Independent
Classifier: Development Status :: 5 - Production/Stable
Requires-Python: >=3.8
License-File: LICENSE
Requires-Dist: thefuzz (>=0.18)
Requires-Dist: attrs
